{
  "channelList": [
    {
      "url": "https://www.ftvnews.com.tw/live/live-video/2/11",
      "name": "民視新聞"
    },
    {
      "url": "https://www.youtube.com/watch?v=wM0g8EoUZ_E",
      "name": "華視新聞"
    },
    {
      "url": "https://www.youtube.com/watch?v=5n0y6b0Q25o",
      "name": "鏡新聞"
    },
    {
      "url": "https://www.youtube.com/watch?v=CKjSm5ZeehE",
      "name": "三立 iNEWS 新聞"
    },
    {
      "url": "https://www.youtube.com/watch?v=WIhgU_mc05A",
      "name": "新唐人"
    },
    {
      "url": "https://www.youtube.com/watch?v=xL0ch83RAK8",
      "name": "台視新聞"
    },
    {
      "url": "https://www.youtube.com/watch?v=6KlRR_DGhmI",
      "name": "公視台語台"
    },
    {
      "url": "https://www.youtube.com/watch?v=4Uc00FPs27M",
      "name": "公共電視"
    },
    {
      "url": "https://www.youtube.com/watch?v=UK81GCw1KE8",
      "name": "木棉花馬拉松1"
    },
    {
      "url": "https://www.youtube.com/watch?v=E0JOmRTFGlE",
      "name": "木棉花馬拉松2"
    },
    {
      "url": "https://www.ftvnews.com.tw/live/live-video/1/litv-ftv07",
      "name": "民視旅遊台"
    },
    {
      "url": "https://www.ftvnews.com.tw/live/live-video/1/4gtv-4gtv001",
      "name": "民視台灣台"
    },
    {
      "url": "https://www.ftvnews.com.tw/live/live-video/1/4gtv-4gtv002",
      "name": "民視無線台"
    },
    {
      "url": "https://www.ftvnews.com.tw/live/live-video/1/4gtv-4gtv004",
      "name": "民視綜藝台"
    },
    {
      "url": "https://www.ftvnews.com.tw/live/live-video/1/4gtv-4gtv003",
      "name": "民視第一台"
    },
    {
      "url": "https://www.youtube.com/watch?v=4HysYHJ6GkY",
      "name": "國會頻道１"
    },
    {
      "url": "https://www.youtube.com/watch?v=RAP4h3q6_Sg",
      "name": "國會頻道２"
    },
    {
      "url": "https://www.youtube.com/user/57ETFN/live",
      "name": "東森財經"
    },
    {
      "url": "https://www.youtube.com/channel/UCp2f7tGJGN6R9Muxipem8Nw/live",
      "name": "寰宇新聞"
    },
    {
      "url": "https://aka03p.akamaized.net/litv/fet001.smil/playlist.m3u8",
      "name": "非凡新聞",
      "header": "Referer: https://fetfriday.svc.litv.tv/"
    },
    {
      "url": "https://www.youtube.com/watch?v=dp8PhLsUcFE",
      "name": "Bloomberg Global Financial News"
    },
    {
      "url": "https://www.youtube.com/watch?v=w_Ma8oQLmSM",
      "name": "ABC News"
    },
    {
      "url": "https://www.youtube.com/watch?v=WoKKG0l8QsQ",
      "name": "KBS News"
    },
    {
      "url": "https://www.youtube.com/watch?v=f0lYkdA-Gtw",
      "name": "NHK WORLD-JAPAN"
    }
  ]
}
